Workbook
Name Slicer_Category: #N/A
Name Slicer_Region: #N/A
Name Slicer_Year: #N/A

Sheet Customers
A1: CustomerID | B1: FirstName | C1: LastName | D1: Gender | E1: BirthDate | F1: City | G1: JoinDate
A2: C001 | B2: Michael | C2: Davis | D2: M | E2: 35319 | F2: Osborneport | G2: 44829
A3: C002 | B3: Michael | C3: Miller | D3: M | E3: 21780 | F3: New Gabrielleport | G3: 44138
A4: C003 | B4: Carol | C4: Hays | D4: F | E4: 38461 | F4: Port Allen | G4: 45334
A5: C004 | B5: Joseph | C5: Ward | D5: M | E5: 33771 | F5: East Edgarborough | G5: 45544
A6: C005 | B6: Jamie | C6: Salinas | D6: M | E6: 33773 | F6: Port Kimberly | G6: 44616
A7: C006 | B7: Danny | C7: Moore | D7: M | E7: 31688 | F7: Costaberg | G7: 44751
A8: C007 | B8: Erin | C8: Walker | D8: M | E8: 31058 | F8: West Jasmine | G8: 44482
A9: C008 | B9: Isaiah | C9: Williams | D9: M | E9: 22233 | F9: New Michaelland | G9: 45720
A10: C009 | B10: Richard | C10: Pacheco | D10: F | E10: 38214 | F10: West Lisaville | G10: 45764
A11: C010 | B11: Catherine | C11: Rice | D11: M | E11: 28106 | F11: West Carol | G11: 45861
A12: C011 | B12: Haley | C12: Williams | D12: M | E12: 35492 | F12: Leburgh | G12: 45058
A13: C012 | B13: Dale | C13: Perry | D13: M | E13: 32850 | F13: Lake Dawn | G13: 44393
... A201: C200 | B201: Ronald | C201: Haley | D201: M | E201: 37249 | F201: Jenniferbury | G201: 45832

Sheet Products
A1: ProductID | B1: ProductName | C1: Category | D1: SubCategory | E1: UnitPrice | F1: CostPrice
A2: P001 | B2: Like Camera | C2: Electronics | D2: Camera | E2: 1673.69 | F2: 1323.38
A3: P002 | B3: Audience Television | C3: Electronics | D3: Television | E3: 818.76 | F3: 527.62
A4: P003 | B4: Here Footwear | C4: Fashion | D4: Footwear | E4: 337.63 | F4: 169.03
A5: P004 | B5: Four Accessories | C5: Fashion | D5: Accessories | E5: 1853.77 | F5: 1363.52
A6: P005 | B6: Knowledge Bags | C6: Fashion | D6: Bags | E6: 1396.22 | F6: 1004.09
A7: P006 | B7: Company Fruits | C7: Groceries | D7: Fruits | E7: 318.05 | F7: 187.34
A8: P007 | B8: Understand Camera | C8: Electronics | D8: Camera | E8: 1474.12 | F8: 764.02
A9: P008 | B9: Recognize Footwear | C9: Fashion | D9: Footwear | E9: 109.78 | F9: 70.59
A10: P009 | B10: Us Snacks | C10: Groceries | D10: Snacks | E10: 123.19 | F10: 80.36
A11: P010 | B11: Step Smartphone | C11: Electronics | D11: Smartphone | E11: 1194.12 | F11: 838.95
A12: P011 | B12: Either Headphones | C12: Electronics | D12: Headphones | E12: 248.57 | F12: 190.67
A13: P012 | B13: Above Camera | C13: Electronics | D13: Camera | E13: 1193.09 | F13: 818.24
... A51: P050 | B51: Maybe Footwear | C51: Fashion | D51: Footwear | E51: 1044.64 | F51: 775.07

Sheet Stores
A1: StoreID | B1: StoreName | C1: City | D1: Region
A2: S001 | B2: MegaMart Jimenezborough | C2: Jimenezborough | D2: South
A3: S002 | B3: MegaMart Peckmouth | C3: Peckmouth | D3: East
A4: S003 | B4: MegaMart New Michele | C4: New Michele | D4: West
A5: S004 | B5: MegaMart Brianahaven | C5: Brianahaven | D5: North
A6: S005 | B6: MegaMart Johnmouth | C6: Johnmouth | D6: East

Sheet Transactions
A1: TransactionID | B1: Date | C1: CustomerID | D1: ProductID | E1: StoreID | F1: Quantity | G1: Discount | H1: PaymentMethod | I1: Gross Revenue | J1: Net Revenue | K1: Total Cost | L1: Profit | M1: ProductName | N1: Month | O1: Year | P1: Category | Q1: SubCategory | R1: UnitPrice | S1: CostPrice | T1: CustomerGender | U1: CustomerBirthday | V1: Age | W1: Age Group | X1: StoreName | Y1: City | Z1: Region
A2: T00001 | B2: 45461 | C2: C160 | D2: P014 | E2: S003 | F2: 1 | G2: 0.1 | H2: Bank Transfer | I2: =Table4[[#This Row],[Quantity]]*Table4[[#This Row],[UnitPrice]] -> 1342.75 | J2: =Table4[[#This Row],[Gross Revenue]]*(1-Table4[[#This Row],[Discount]]) -> 1208.475 | K2: =Table4[[#This Row],[Quantity]]*Table4[[#This Row],[CostPrice]] -> 797.94 | L2: =Table4[[#This Row],[Net Revenue]]-Table4[[#This Row],[Total Cost]] -> 410.535 | M2: =_xlfn.XLOOKUP(Table4[[#This Row],[ProductID]], Products!A:A,Products!B:B, "Not Found") -> Add Clothing | N2: =TEXT(Table4[[#This Row],[Date]], "mmm") -> Jun | O2: =TEXT(Table4[[#This Row],[Date]], "yyyy") -> 2024 | P2: =_xlfn.XLOOKUP(Table4[[#This Row],[ProductID]],Products!A:A,Products!C:C, "Not Found") -> Fashion | Q2: =_xlfn.XLOOKUP(Table4[[#This Row],[ProductID]],Products!A:A,Products!D:D,"Not Found") -> Clothing | R2: =_xlfn.XLOOKUP(Table4[[#This Row],[ProductID]],Products!A:A,Products!E:E,"Not Found") -> 1342.75 | S2: =_xlfn.XLOOKUP(Table4[[#This Row],[ProductID]],Products!A:A,Products!F:F, "Not Found") -> 797.94 | T2: =_xlfn.XLOOKUP(Table4[[#This Row],[CustomerID]],Customers!A:A,Customers!D:D, "Not Found") -> M | U2: =_xlfn.XLOOKUP(Table4[[#This Row],[CustomerID]],Customers!A:A,Customers!E:E, "Not Found") -> 33491 | V2: =DATEDIF(Table4[[#This Row],[CustomerBirthday]], TODAY(), "Y") -> 34 | W2: {=_xlfn.IFS(Table4[[#This Row],[Age]]<25, "Under 25",Table4[[#This Row],[Age]]=34, "25-34", Table4[[#This Row],[Age]]<=49, "35-49", Table4[[#This Row],[Age]]<=64, "50-64", Table4[[#This Row],[Age]]>=65, "65+")} -> 25-34 | X2: =_xlfn.XLOOKUP(Table4[[#This Row],[StoreID]],Stores!A:A,Stores!B:B, "Not found") -> MegaMart New Michele | Y2: =_xlfn.XLOOKUP(Table4[[#This Row],[StoreID]],Stores!A:A,Stores!C:C, "Not Found") -> New Michele | Z2: =_xlfn.XLOOKUP(Table4[[#This Row],[StoreID]],Stores!A:A,Stores!D:D, "Not Found") -> West
A3: T00002 | B3: 45232 | C3: C171 | D3: P030 | E3: S004 | F3: 3 | G3: 0.15 | H3: Bank Transfer | I3: =Table4[[#This Row],[Quantity]]*Table4[[#This Row],[UnitPrice]] -> 87.72 | J3: =Table4[[#This Row],[Gross Revenue]]*(1-Table4[[#This Row],[Discount]]) -> 74.562 | K3: =Table4[[#This Row],[Quantity]]*Table4[[#This Row],[CostPrice]] -> 45.84 | L3: =Table4[[#This Row],[Net Revenue]]-Table4[[#This Row],[Total Cost]] -> 28.722 | M3: =_xlfn.XLOOKUP(Table4[[#This Row],[ProductID]], Products!A:A,Products!B:B, "Not Found") -> National Watches | N3: =TEXT(Table4[[#This Row],[Date]], "mmm") -> Nov | O3: =TEXT(Table4[[#This Row],[Date]], "yyyy") -> 2023 | P3: =_xlfn.XLOOKUP(Table4[[#This Row],[ProductID]],Products!A:A,Products!C:C, "Not Found") -> Fashion | Q3: =_xlfn.XLOOKUP(Table4[[#This Row],[ProductID]],Products!A:A,Products!D:D,"Not Found") -> Watches | R3: =_xlfn.XLOOKUP(Table4[[#This Row],[ProductID]],Products!A:A,Products!E:E,"Not Found") -> 29.24 | S3: =_xlfn.XLOOKUP(Table4[[#This Row],[ProductID]],Products!A:A,Products!F:F, "Not Found") -> 15.28 | T3: =_xlfn.XLOOKUP(Table4[[#This Row],[CustomerID]],Customers!A:A,Customers!D:D, "Not Found") -> M | U3: =_xlfn.XLOOKUP(Table4[[#This Row],[CustomerID]],Customers!A:A,Customers!E:E, "Not Found") -> 34043 | V3: =DATEDIF(Table4[[#This Row],[CustomerBirthday]], TODAY(), "Y") -> 33 | W3: {=_xlfn.IFS(Table4[[#This Row],[Age]]<25, "Under 25",Table4[[#This Row],[Age]]=34, "25-34", Table4[[#This Row],[Age]]<=49, "35-49", Table4[[#This Row],[Age]]<=64, "50-64", Table4[[#This Row],[Age]]>=65, "65+")} -> 35-49 | X3: =_xlfn.XLOOKUP(Table4[[#This Row],[StoreID]],Stores!A:A,Stores!B:B, "Not found") -> MegaMart Brianahaven | Y3: =_xlfn.XLOOKUP(Table4[[#This Row],[StoreID]],Stores!A:A,Stores!C:C, "Not Found") -> Brianahaven | Z3: =_xlfn.XLOOKUP(Table4[[#This Row],[StoreID]],Stores!A:A,Stores!D:D, "Not Found") -> North
A4: T00003 | B4: 45379 | C4: C142 | D4: P002 | E4: S002 | F4: 2 | G4: 0.15 | H4: Mobile Money | I4: =Table4[[#This Row],[Quantity]]*Table4[[#This Row],[UnitPrice]] -> 1637.52 | J4: =Table4[[#This Row],[Gross Revenue]]*(1-Table4[[#This Row],[Discount]]) -> 1391.892 | K4: =Table4[[#This Row],[Quantity]]*Table4[[#This Row],[CostPrice]] -> 1055.24 | L4: =Table4[[#This Row],[Net Revenue]]-Table4[[#This Row],[Total Cost]] -> 336.652 | M4: =_xlfn.XLOOKUP(Table4[[#This Row],[ProductID]], Products!A:A,Products!B:B, "Not Found") -> Audience Television | N4: =TEXT(Table4[[#This Row],[Date]], "mmm") -> Mar | O4: =TEXT(Table4[[#This Row],[Date]], "yyyy") -> 2024 | P4: =_xlfn.XLOOKUP(Table4[[#This Row],[ProductID]],Products!A:A,Products!C:C, "Not Found") -> Electronics | Q4: =_xlfn.XLOOKUP(Table4[[#This Row],[ProductID]],Products!A:A,Products!D:D,"Not Found") -> Television | R4: =_xlfn.XLOOKUP(Table4[[#This Row],[ProductID]],Products!A:A,Products!E:E,"Not Found") -> 818.76 | S4: =_xlfn.XLOOKUP(Table4[[#This Row],[ProductID]],Products!A:A,Products!F:F, "Not Found") -> 527.62 | T4: =_xlfn.XLOOKUP(Table4[[#This Row],[CustomerID]],Customers!A:A,Customers!D:D, "Not Found") -> M | U4: =_xlfn.XLOOKUP(Table4[[#This Row],[CustomerID]],Customers!A:A,Customers!E:E, "Not Found") -> 38558 | V4: =DATEDIF(Table4[[#This Row],[CustomerBirthday]], TODAY(), "Y") -> 21 | W4: {=_xlfn.IFS(Table4[[#This Row],[Age]]<25, "Under 25",Table4[[#This Row],[Age]]=34, "25-34", Table4[[#This Row],[Age]]<=49, "35-49", Table4[[#This Row],[Age]]<=64, "50-64", Table4[[#This Row],[Age]]>=65, "65+")} -> Under 25 | X4: =_xlfn.XLOOKUP(Table4[[#This Row],[StoreID]],Stores!A:A,Stores!B:B, "Not found") -> MegaMart Peckmouth | Y4: =_xlfn.XLOOKUP(Table4[[#This Row],[StoreID]],Stores!A:A,Stores!C:C, "Not Found") -> Peckmouth | Z4: =_xlfn.XLOOKUP(Table4[[#This Row],[StoreID]],Stores!A:A,Stores!D:D, "Not Found") -> East
A5: T00004 | B5: 45458 | C5: C174 | D5: P050 | E5: S002 | F5: 5 | G5: 0.1 | H5: Mobile Money | I5: =Table4[[#This Row],[Quantity]]*Table4[[#This Row],[UnitPrice]] -> 5223.2 | J5: =Table4[[#This Row],[Gross Revenue]]*(1-Table4[[#This Row],[Discount]]) -> 4700.88 | K5: =Table4[[#This Row],[Quantity]]*Table4[[#This Row],[CostPrice]] -> 3875.35 | L5: =Table4[[#This Row],[Net Revenue]]-Table4[[#This Row],[Total Cost]] -> 825.53 | M5: =_xlfn.XLOOKUP(Table4[[#This Row],[ProductID]], Products!A:A,Products!B:B, "Not Found") -> Maybe Footwear | N5: =TEXT(Table4[[#This Row],[Date]], "mmm") -> Jun | O5: =TEXT(Table4[[#This Row],[Date]], "yyyy") -> 2024 | P5: =_xlfn.XLOOKUP(Table4[[#This Row],[ProductID]],Products!A:A,Products!C:C, "Not Found") -> Fashion | Q5: =_xlfn.XLOOKUP(Table4[[#This Row],[ProductID]],Products!A:A,Products!D:D,"Not Found") -> Footwear | R5: =_xlfn.XLOOKUP(Table4[[#This Row],[ProductID]],Products!A:A,Products!E:E,"Not Found") -> 1044.64 | S5: =_xlfn.XLOOKUP(Table4[[#This Row],[ProductID]],Products!A:A,Products!F:F, "Not Found") -> 775.07 | T5: =_xlfn.XLOOKUP(Table4[[#This Row],[CustomerID]],Customers!A:A,Customers!D:D, "Not Found") -> M | U5: =_xlfn.XLOOKUP(Table4[[#This Row],[CustomerID]],Customers!A:A,Customers!E:E, "Not Found") -> 38540 | V5: =DATEDIF(Table4[[#This Row],[CustomerBirthday]], TODAY(), "Y") -> 21 | W5: {=_xlfn.IFS(Table4[[#This Row],[Age]]<25, "Under 25",Table4[[#This Row],[Age]]=34, "25-34", Table4[[#This Row],[Age]]<=49, "35-49", Table4[[#This Row],[Age]]<=64, "50-64", Table4[[#This Row],[Age]]>=65, "65+")} -> Under 25 | X5: =_xlfn.XLOOKUP(Table4[[#This Row],[StoreID]],Stores!A:A,Stores!B:B, "Not found") -> MegaMart Peckmouth | Y5: =_xlfn.XLOOKUP(Table4[[#This Row],[StoreID]],Stores!A:A,Stores!C:C, "Not Found") -> Peckmouth | Z5: =_xlfn.XLOOKUP(Table4[[#This Row],[StoreID]],Stores!A:A,Stores!D:D, "Not Found") -> East
A6: T00005 | B6: 45533 | C6: C141 | D6: P036 | E6: S001 | F6: 3 | G6: 0.1 | H6: Credit Card | I6: =Table4[[#This Row],[Quantity]]*Table4[[#This Row],[UnitPrice]] -> 4504.38 | J6: =Table4[[#This Row],[Gross Revenue]]*(1-Table4[[#This Row],[Discount]]) -> 4053.942 | K6: =Table4[[#This Row],[Quantity]]*Table4[[#This Row],[CostPrice]] -> 3503.19 | L6: =Table4[[#This Row],[Net Revenue]]-Table4[[#This Row],[Total Cost]] -> 550.752 | M6: =_xlfn.XLOOKUP(Table4[[#This Row],[ProductID]], Products!A:A,Products!B:B, "Not Found") -> New Watches | N6: =TEXT(Table4[[#This Row],[Date]], "mmm") -> Aug | O6: =TEXT(Table4[[#This Row],[Date]], "yyyy") -> 2024 | P6: =_xlfn.XLOOKUP(Table4[[#This Row],[ProductID]],Products!A:A,Products!C:C, "Not Found") -> Fashion | Q6: =_xlfn.XLOOKUP(Table4[[#This Row],[ProductID]],Products!A:A,Products!D:D,"Not Found") -> Watches | R6: =_xlfn.XLOOKUP(Table4[[#This Row],[ProductID]],Products!A:A,Products!E:E,"Not Found") -> 1501.46 | S6: =_xlfn.XLOOKUP(Table4[[#This Row],[ProductID]],Products!A:A,Products!F:F, "Not Found") -> 1167.73 | T6: =_xlfn.XLOOKUP(Table4[[#This Row],[CustomerID]],Customers!A:A,Customers!D:D, "Not Found") -> F | U6: =_xlfn.XLOOKUP(Table4[[#This Row],[CustomerID]],Customers!A:A,Customers!E:E, "Not Found") -> 28708 | V6: =DATEDIF(Table4[[#This Row],[CustomerBirthday]], TODAY(), "Y") -> 47 | W6: {=_xlfn.IFS(Table4[[#This Row],[Age]]<25, "Under 25",Table4[[#This Row],[Age]]=34, "25-34", Table4[[#This Row],[Age]]<=49, "35-49", Table4[[#This Row],[Age]]<=64, "50-64", Table4[[#This Row],[Age]]>=65, "65+")} -> 35-49 | X6: =_xlfn.XLOOKUP(Table4[[#This Row],[StoreID]],Stores!A:A,Stores!B:B, "Not found") -> MegaMart Jimenezborough | Y6: =_xlfn.XLOOKUP(Table4[[#This Row],[StoreID]],Stores!A:A,Stores!C:C, "Not Found") -> Jimenezborough | Z6: =_xlfn.XLOOKUP(Table4[[#This Row],[StoreID]],Stores!A:A,Stores!D:D, "Not Found") -> South
A7: T00006 | B7: 45744 | C7: C111 | D7: P036 | E7: S005 | F7: 5 | G7: 0.1 | H7: Mobile Money | I7: =Table4[[#This Row],[Quantity]]*Table4[[#This Row],[UnitPrice]] -> 7507.3 | J7: =Table4[[#This Row],[Gross Revenue]]*(1-Table4[[#This Row],[Discount]]) -> 6756.57 | K7: =Table4[[#This Row],[Quantity]]*Table4[[#This Row],[CostPrice]] -> 5838.65 | L7: =Table4[[#This Row],[Net Revenue]]-Table4[[#This Row],[Total Cost]] -> 917.92 | M7: =_xlfn.XLOOKUP(Table4[[#This Row],[ProductID]], Products!A:A,Products!B:B, "Not Found") -> New Watches | N7: =TEXT(Table4[[#This Row],[Date]], "mmm") -> Mar | O7: =TEXT(Table4[[#This Row],[Date]], "yyyy") -> 2025 | P7: =_xlfn.XLOOKUP(Table4[[#This Row],[ProductID]],Products!A:A,Products!C:C, "Not Found") -> Fashion | Q7: =_xlfn.XLOOKUP(Table4[[#This Row],[ProductID]],Products!A:A,Products!D:D,"Not Found") -> Watches | R7: =_xlfn.XLOOKUP(Table4[[#This Row],[ProductID]],Products!A:A,Products!E:E,"Not Found") -> 1501.46 | S7: =_xlfn.XLOOKUP(Table4[[#This Row],[ProductID]],Products!A:A,Products!F:F, "Not Found") -> 1167.73 | T7: =_xlfn.XLOOKUP(Table4[[#This Row],[CustomerID]],Customers!A:A,Customers!D:D, "Not Found") -> M | U7: =_xlfn.XLOOKUP(Table4[[#This Row],[CustomerID]],Customers!A:A,Customers!E:E, "Not Found") -> 34163 | V7: =DATEDIF(Table4[[#This Row],[CustomerBirthday]], TODAY(), "Y") -> 33 | W7: {=_xlfn.IFS(Table4[[#This Row],[Age]]<25, "Under 25",Table4[[#This Row],[Age]]=34, "25-34", Table4[[#This Row],[Age]]<=49, "35-49", Table4[[#This Row],[Age]]<=64, "50-64", Table4[[#This Row],[Age]]>=65, "65+")} -> 35-49 | X7: =_xlfn.XLOOKUP(Table4[[#This Row],[StoreID]],Stores!A:A,Stores!B:B, "Not found") -> MegaMart Johnmouth | Y7: =_xlfn.XLOOKUP(Table4[[#This Row],[StoreID]],Stores!A:A,Stores!C:C, "Not Found") -> Johnmouth | Z7: =_xlfn.XLOOKUP(Table4[[#This Row],[StoreID]],Stores!A:A,Stores!D:D, "Not Found") -> East
A8: T00007 | B8: 45605 | C8: C114 | D8: P009 | E8: S004 | F8: 2 | G8: 0.15 | H8: Credit Card | I8: =Table4[[#This Row],[Quantity]]*Table4[[#This Row],[UnitPrice]] -> 246.38 | J8: =Table4[[#This Row],[Gross Revenue]]*(1-Table4[[#This Row],[Discount]]) -> 209.423 | K8: =Table4[[#This Row],[Quantity]]*Table4[[#This Row],[CostPrice]] -> 160.72 | L8: =Table4[[#This Row],[Net Revenue]]-Table4[[#This Row],[Total Cost]] -> 48.703 | M8: =_xlfn.XLOOKUP(Table4[[#This Row],[ProductID]], Products!A:A,Products!B:B, "Not Found") -> Us Snacks | N8: =TEXT(Table4[[#This Row],[Date]], "mmm") -> Nov | O8: =TEXT(Table4[[#This Row],[Date]], "yyyy") -> 2024 | P8: =_xlfn.XLOOKUP(Table4[[#This Row],[ProductID]],Products!A:A,Products!C:C, "Not Found") -> Groceries | Q8: =_xlfn.XLOOKUP(Table4[[#This Row],[ProductID]],Products!A:A,Products!D:D,"Not Found") -> Snacks | R8: =_xlfn.XLOOKUP(Table4[[#This Row],[ProductID]],Products!A:A,Products!E:E,"Not Found") -> 123.19 | S8: =_xlfn.XLOOKUP(Table4[[#This Row],[ProductID]],Products!A:A,Products!F:F, "Not Found") -> 80.36 | T8: =_xlfn.XLOOKUP(Table4[[#This Row],[CustomerID]],Customers!A:A,Customers!D:D, "Not Found") -> F | U8: =_xlfn.XLOOKUP(Table4[[#This Row],[CustomerID]],Customers!A:A,Customers!E:E, "Not Found") -> 29406 | V8: =DATEDIF(Table4[[#This Row],[CustomerBirthday]], TODAY(), "Y") -> 46 | W8: {=_xlfn.IFS(Table4[[#This Row],[Age]]<25, "Under 25",Table4[[#This Row],[Age]]=34, "25-34", Table4[[#This Row],[Age]]<=49, "35-49", Table4[[#This Row],[Age]]<=64, "50-64", Table4[[#This Row],[Age]]>=65, "65+")} -> 35-49 | X8: =_xlfn.XLOOKUP(Table4[[#This Row],[StoreID]],Stores!A:A,Stores!B:B, "Not found") -> MegaMart Brianahaven | Y8: =_xlfn.XLOOKUP(Table4[[#This Row],[StoreID]],Stores!A:A,Stores!C:C, "Not Found") -> Brianahaven | Z8: =_xlfn.XLOOKUP(Table4[[#This Row],[StoreID]],Stores!A:A,Stores!D:D, "Not Found") -> North
A9: T00008 | B9: 45440 | C9: C169 | D9: P005 | E9: S001 | F9: 3 | G9: 0.1 | H9: Cash | I9: =Table4[[#This Row],[Quantity]]*Table4[[#This Row],[UnitPrice]] -> 4188.66 | J9: =Table4[[#This Row],[Gross Revenue]]*(1-Table4[[#This Row],[Discount]]) -> 3769.794 | K9: =Table4[[#This Row],[Quantity]]*Table4[[#This Row],[CostPrice]] -> 3012.27 | L9: =Table4[[#This Row],[Net Revenue]]-Table4[[#This Row],[Total Cost]] -> 757.524 | M9: =_xlfn.XLOOKUP(Table4[[#This Row],[ProductID]], Products!A:A,Products!B:B, "Not Found") -> Knowledge Bags | N9: =TEXT(Table4[[#This Row],[Date]], "mmm") -> May | O9: =TEXT(Table4[[#This Row],[Date]], "yyyy") -> 2024 | P9: =_xlfn.XLOOKUP(Table4[[#This Row],[ProductID]],Products!A:A,Products!C:C, "Not Found") -> Fashion | Q9: =_xlfn.XLOOKUP(Table4[[#This Row],[ProductID]],Products!A:A,Products!D:D,"Not Found") -> Bags | R9: =_xlfn.XLOOKUP(Table4[[#This Row],[ProductID]],Products!A:A,Products!E:E,"Not Found") -> 1396.22 | S9: =_xlfn.XLOOKUP(Table4[[#This Row],[ProductID]],Products!A:A,Products!F:F, "Not Found") -> 1004.09 | T9: =_xlfn.XLOOKUP(Table4[[#This Row],[CustomerID]],Customers!A:A,Customers!D:D, "Not Found") -> M | U9: =_xlfn.XLOOKUP(Table4[[#This Row],[CustomerID]],Customers!A:A,Customers!E:E, "Not Found") -> 24638 | V9: =DATEDIF(Table4[[#This Row],[CustomerBirthday]], TODAY(), "Y") -> 59 | W9: {=_xlfn.IFS(Table4[[#This Row],[Age]]<25, "Under 25",Table4[[#This Row],[Age]]=34, "25-34", Table4[[#This Row],[Age]]<=49, "35-49", Table4[[#This Row],[Age]]<=64, "50-64", Table4[[#This Row],[Age]]>=65, "65+")} -> 50-64 | X9: =_xlfn.XLOOKUP(Table4[[#This Row],[StoreID]],Stores!A:A,Stores!B:B, "Not found") -> MegaMart Jimenezborough | Y9: =_xlfn.XLOOKUP(Table4[[#This Row],[StoreID]],Stores!A:A,Stores!C:C, "Not Found") -> Jimenezborough | Z9: =_xlfn.XLOOKUP(Table4[[#This Row],[StoreID]],Stores!A:A,Stores!D:D, "Not Found") -> South
A10: T00009 | B10: 45539 | C10: C193 | D10: P035 | E10: S002 | F10: 3 | G10: 0.05 | H10: Credit Card | I10: =Table4[[#This Row],[Quantity]]*Table4[[#This Row],[UnitPrice]] -> 4687.29 | J10: =Table4[[#This Row],[Gross Revenue]]*(1-Table4[[#This Row],[Discount]]) -> 4452.9255 | K10: =Table4[[#This Row],[Quantity]]*Table4[[#This Row],[CostPrice]] -> 3586.89 | L10: =Table4[[#This Row],[Net Revenue]]-Table4[[#This Row],[Total Cost]] -> 866.0355 | M10: =_xlfn.XLOOKUP(Table4[[#This Row],[ProductID]], Products!A:A,Products!B:B, "Not Found") -> Chair Laptop | N10: =TEXT(Table4[[#This Row],[Date]], "mmm") -> Sep | O10: =TEXT(Table4[[#This Row],[Date]], "yyyy") -> 2024 | P10: =_xlfn.XLOOKUP(Table4[[#This Row],[ProductID]],Products!A:A,Products!C:C, "Not Found") -> Electronics | Q10: =_xlfn.XLOOKUP(Table4[[#This Row],[ProductID]],Products!A:A,Products!D:D,"Not Found") -> Laptop | R10: =_xlfn.XLOOKUP(Table4[[#This Row],[ProductID]],Products!A:A,Products!E:E,"Not Found") -> 1562.43 | S10: =_xlfn.XLOOKUP(Table4[[#This Row],[ProductID]],Products!A:A,Products!F:F, "Not Found") -> 1195.63 | T10: =_xlfn.XLOOKUP(Table4[[#This Row],[CustomerID]],Customers!A:A,Customers!D:D, "Not Found") -> F | U10: =_xlfn.XLOOKUP(Table4[[#This Row],[CustomerID]],Customers!A:A,Customers!E:E, "Not Found") -> 25513 | V10: =DATEDIF(Table4[[#This Row],[CustomerBirthday]], TODAY(), "Y") -> 56 | W10: {=_xlfn.IFS(Table4[[#This Row],[Age]]<25, "Under 25",Table4[[#This Row],[Age]]=34, "25-34", Table4[[#This Row],[Age]]<=49, "35-49", Table4[[#This Row],[Age]]<=64, "50-64", Table4[[#This Row],[Age]]>=65, "65+")} -> 50-64 | X10: =_xlfn.XLOOKUP(Table4[[#This Row],[StoreID]],Stores!A:A,Stores!B:B, "Not found") -> MegaMart Peckmouth | Y10: =_xlfn.XLOOKUP(Table4[[#This Row],[StoreID]],Stores!A:A,Stores!C:C, "Not Found") -> Peckmouth | Z10: =_xlfn.XLOOKUP(Table4[[#This Row],[StoreID]],Stores!A:A,Stores!D:D, "Not Found") -> East
A11: T00010 | B11: 45459 | C11: C038 | D11: P045 | E11: S001 | F11: 1 | G11: 0.05 | H11: Mobile Money | I11: =Table4[[#This Row],[Quantity]]*Table4[[#This Row],[UnitPrice]] -> 1879.08 | J11: =Table4[[#This Row],[Gross Revenue]]*(1-Table4[[#This Row],[Discount]]) -> 1785.126 | K11: =Table4[[#This Row],[Quantity]]*Table4[[#This Row],[CostPrice]] -> 1004.56 | L11: =Table4[[#This Row],[Net Revenue]]-Table4[[#This Row],[Total Cost]] -> 780.566 | M11: =_xlfn.XLOOKUP(Table4[[#This Row],[ProductID]], Products!A:A,Products!B:B, "Not Found") -> Set Dairy | N11: =TEXT(Table4[[#This Row],[Date]], "mmm") -> Jun | O11: =TEXT(Table4[[#This Row],[Date]], "yyyy") -> 2024 | P11: =_xlfn.XLOOKUP(Table4[[#This Row],[ProductID]],Products!A:A,Products!C:C, "Not Found") -> Groceries | Q11: =_xlfn.XLOOKUP(Table4[[#This Row],[ProductID]],Products!A:A,Products!D:D,"Not Found") -> Dairy | R11: =_xlfn.XLOOKUP(Table4[[#This Row],[ProductID]],Products!A:A,Products!E:E,"Not Found") -> 1879.08 | S11: =_xlfn.XLOOKUP(Table4[[#This Row],[ProductID]],Products!A:A,Products!F:F, "Not Found") -> 1004.56 | T11: =_xlfn.XLOOKUP(Table4[[#This Row],[CustomerID]],Customers!A:A,Customers!D:D, "Not Found") -> M | U11: =_xlfn.XLOOKUP(Table4[[#This Row],[CustomerID]],Customers!A:A,Customers!E:E, "Not Found") -> 27138 | V11: =DATEDIF(Table4[[#This Row],[CustomerBirthday]], TODAY(), "Y") -> 52 | W11: {=_xlfn.IFS(Table4[[#This Row],[Age]]<25, "Under 25",Table4[[#This Row],[Age]]=34, "25-34", Table4[[#This Row],[Age]]<=49, "35-49", Table4[[#This Row],[Age]]<=64, "50-64", Table4[[#This Row],[Age]]>=65, "65+")} -> 50-64 | X11: =_xlfn.XLOOKUP(Table4[[#This Row],[StoreID]],Stores!A:A,Stores!B:B, "Not found") -> MegaMart Jimenezborough | Y11: =_xlfn.XLOOKUP(Table4[[#This Row],[StoreID]],Stores!A:A,Stores!C:C, "Not Found") -> Jimenezborough | Z11: =_xlfn.XLOOKUP(Table4[[#This Row],[StoreID]],Stores!A:A,Stores!D:D, "Not Found") -> South
A12: T00011 | B12: 45725 | C12: C157 | D12: P022 | E12: S001 | F12: 4 | G12: 0.15 | H12: Credit Card | I12: =Table4[[#This Row],[Quantity]]*Table4[[#This Row],[UnitPrice]] -> 102.28 | J12: =Table4[[#This Row],[Gross Revenue]]*(1-Table4[[#This Row],[Discount]]) -> 86.938 | K12: =Table4[[#This Row],[Quantity]]*Table4[[#This Row],[CostPrice]] -> 76.2 | L12: =Table4[[#This Row],[Net Revenue]]-Table4[[#This Row],[Total Cost]] -> 10.738 | M12: =_xlfn.XLOOKUP(Table4[[#This Row],[ProductID]], Products!A:A,Products!B:B, "Not Found") -> How Vegetables | N12: =TEXT(Table4[[#This Row],[Date]], "mmm") -> Mar | O12: =TEXT(Table4[[#This Row],[Date]], "yyyy") -> 2025 | P12: =_xlfn.XLOOKUP(Table4[[#This Row],[ProductID]],Products!A:A,Products!C:C, "Not Found") -> Groceries | Q12: =_xlfn.XLOOKUP(Table4[[#This Row],[ProductID]],Products!A:A,Products!D:D,"Not Found") -> Vegetables | R12: =_xlfn.XLOOKUP(Table4[[#This Row],[ProductID]],Products!A:A,Products!E:E,"Not Found") -> 25.57 | S12: =_xlfn.XLOOKUP(Table4[[#This Row],[ProductID]],Products!A:A,Products!F:F, "Not Found") -> 19.05 | T12: =_xlfn.XLOOKUP(Table4[[#This Row],[CustomerID]],Customers!A:A,Customers!D:D, "Not Found") -> M | U12: =_xlfn.XLOOKUP(Table4[[#This Row],[CustomerID]],Customers!A:A,Customers!E:E, "Not Found") -> 24092 | V12: =DATEDIF(Table4[[#This Row],[CustomerBirthday]], TODAY(), "Y") -> 60 | W12: {=_xlfn.IFS(Table4[[#This Row],[Age]]<25, "Under 25",Table4[[#This Row],[Age]]=34, "25-34", Table4[[#This Row],[Age]]<=49, "35-49", Table4[[#This Row],[Age]]<=64, "50-64", Table4[[#This Row],[Age]]>=65, "65+")} -> 50-64 | X12: =_xlfn.XLOOKUP(Table4[[#This Row],[StoreID]],Stores!A:A,Stores!B:B, "Not found") -> MegaMart Jimenezborough | Y12: =_xlfn.XLOOKUP(Table4[[#This Row],[StoreID]],Stores!A:A,Stores!C:C, "Not Found") -> Jimenezborough | Z12: =_xlfn.XLOOKUP(Table4[[#This Row],[StoreID]],Stores!A:A,Stores!D:D, "Not Found") -> South
A13: T00012 | B13: 45449 | C13: C184 | D13: P042 | E13: S004 | F13: 4 | G13: 0.15 | H13: Credit Card | I13: =Table4[[#This Row],[Quantity]]*Table4[[#This Row],[UnitPrice]] -> 1814.48 | J13: =Table4[[#This Row],[Gross Revenue]]*(1-Table4[[#This Row],[Discount]]) -> 1542.308 | K13: =Table4[[#This Row],[Quantity]]*Table4[[#This Row],[CostPrice]] -> 1266.52 | L13: =Table4[[#This Row],[Net Revenue]]-Table4[[#This Row],[Total Cost]] -> 275.788 | M13: =_xlfn.XLOOKUP(Table4[[#This Row],[ProductID]], Products!A:A,Products!B:B, "Not Found") -> Maybe Clothing | N13: =TEXT(Table4[[#This Row],[Date]], "mmm") -> Jun | O13: =TEXT(Table4[[#This Row],[Date]], "yyyy") -> 2024 | P13: =_xlfn.XLOOKUP(Table4[[#This Row],[ProductID]],Products!A:A,Products!C:C, "Not Found") -> Fashion | Q13: =_xlfn.XLOOKUP(Table4[[#This Row],[ProductID]],Products!A:A,Products!D:D,"Not Found") -> Clothing | R13: =_xlfn.XLOOKUP(Table4[[#This Row],[ProductID]],Products!A:A,Products!E:E,"Not Found") -> 453.62 | S13: =_xlfn.XLOOKUP(Table4[[#This Row],[ProductID]],Products!A:A,Products!F:F, "Not Found") -> 316.63 | T13: =_xlfn.XLOOKUP(Table4[[#This Row],[CustomerID]],Customers!A:A,Customers!D:D, "Not Found") -> M | U13: =_xlfn.XLOOKUP(Table4[[#This Row],[CustomerID]],Customers!A:A,Customers!E:E, "Not Found") -> 37724 | V13: =DATEDIF(Table4[[#This Row],[CustomerBirthday]], TODAY(), "Y") -> 23 | W13: {=_xlfn.IFS(Table4[[#This Row],[Age]]<25, "Under 25",Table4[[#This Row],[Age]]=34, "25-34", Table4[[#This Row],[Age]]<=49, "35-49", Table4[[#This Row],[Age]]<=64, "50-64", Table4[[#This Row],[Age]]>=65, "65+")} -> Under 25 | X13: =_xlfn.XLOOKUP(Table4[[#This Row],[StoreID]],Stores!A:A,Stores!B:B, "Not found") -> MegaMart Brianahaven | Y13: =_xlfn.XLOOKUP(Table4[[#This Row],[StoreID]],Stores!A:A,Stores!C:C, "Not Found") -> Brianahaven | Z13: =_xlfn.XLOOKUP(Table4[[#This Row],[StoreID]],Stores!A:A,Stores!D:D, "Not Found") -> North
... A5001: T05000 | B5001: 45489 | C5001: C053 | D5001: P034 | E5001: S004 | F5001: 5 | G5001: 0.15 | H5001: Cash | I5001: =Table4[[#This Row],[Quantity]]*Table4[[#This Row],[UnitPrice]] -> 2140.25 | J5001: =Table4[[#This Row],[Gross Revenue]]*(1-Table4[[#This Row],[Discount]]) -> 1819.2125 | K5001: =Table4[[#This Row],[Quantity]]*Table4[[#This Row],[CostPrice]] -> 1230.35 | L5001: =Table4[[#This Row],[Net Revenue]]-Table4[[#This Row],[Total Cost]] -> 588.8625 | M5001: =_xlfn.XLOOKUP(Table4[[#This Row],[ProductID]], Products!A:A,Products!B:B, "Not Found") -> Everything Laptop | N5001: =TEXT(Table4[[#This Row],[Date]], "mmm") -> Jul | O5001: =TEXT(Table4[[#This Row],[Date]], "yyyy") -> 2024 | P5001: =_xlfn.XLOOKUP(Table4[[#This Row],[ProductID]],Products!A:A,Products!C:C, "Not Found") -> Electronics | Q5001: =_xlfn.XLOOKUP(Table4[[#This Row],[ProductID]],Products!A:A,Products!D:D,"Not Found") -> Laptop | R5001: =_xlfn.XLOOKUP(Table4[[#This Row],[ProductID]],Products!A:A,Products!E:E,"Not Found") -> 428.05 | S5001: =_xlfn.XLOOKUP(Table4[[#This Row],[ProductID]],Products!A:A,Products!F:F, "Not Found") -> 246.07 | T5001: =_xlfn.XLOOKUP(Table4[[#This Row],[CustomerID]],Customers!A:A,Customers!D:D, "Not Found") -> F | U5001: =_xlfn.XLOOKUP(Table4[[#This Row],[CustomerID]],Customers!A:A,Customers!E:E, "Not Found") -> 35905 | V5001: =DATEDIF(Table4[[#This Row],[CustomerBirthday]], TODAY(), "Y") -> 28 | W5001: {=_xlfn.IFS(Table4[[#This Row],[Age]]<25, "Under 25",Table4[[#This Row],[Age]]=34, "25-34", Table4[[#This Row],[Age]]<=49, "35-49", Table4[[#This Row],[Age]]<=64, "50-64", Table4[[#This Row],[Age]]>=65, "65+")} -> 35-49 | X5001: =_xlfn.XLOOKUP(Table4[[#This Row],[StoreID]],Stores!A:A,Stores!B:B, "Not found") -> MegaMart Brianahaven | Y5001: =_xlfn.XLOOKUP(Table4[[#This Row],[StoreID]],Stores!A:A,Stores!C:C, "Not Found") -> Brianahaven | Z5001: =_xlfn.XLOOKUP(Table4[[#This Row],[StoreID]],Stores!A:A,Stores!D:D, "Not Found") -> North

Sheet Pivot_tables
B1: Total Sales | D1: By Category
B2: Sum of Net Revenue | D2: Category | E2: SubCategory | F2: Sum of Profit | H2: Month | I2: Total Sales | J2: Total Profit | L2: Region | M2: Total Sales | N2: Total Profit | P2: StoreName | Q2: Sum of Profit | S2: Age Group | T2: Sales | V2: CustomerGender | W2: Sum of Net Revenue
B3: 5095204 | D3: Groceries | E3: Fruits | F3: 8672.23 | H3: Jan | I3: 628306.77 | J3: 171331.77 | L3: East | M3: 1995474 | N3: 533424.59 | P3: Peckmouth | Q3: 253983.8 | S3: 25-34 | T3: 155262.44 | V3: Female | W3: 2162497.3
E4: Vegetables | F4: 13838.364 | H4: Feb | I4: 516524.24 | J4: 142697.23 | L4: North | M4: 1016186.7 | N4: 277380.9 | P4: Jimenezborough | Q4: 266180.94 | S4: 35-49 | T4: 2094270.1 | V4: Male | W4: 2932706.7
B5: Total Profit | E5: Snacks | F5: 23811.955 | H5: Mar | I5: 585784.73 | J5: 164334.96 | L5: South | M5: 1026200.9 | N5: 266180.94 | P5: Brianahaven | Q5: 277380.9 | S5: 50-64 | T5: 1490648.5 | V5: Grand Total | W5: 5095204
B6: Sum of Profit | E6: Dairy | F6: 161683.94 | H6: Apr | I6: 708233.48 | J6: 185494.51 | L6: West | M6: 1057342.4 | N6: 287036.32 | P6: Johnmouth | Q6: 279440.8 | S6: 65+ | T6: 737161.21
B7: 1364022.7 | D7: Groceries Total | F7: 208006.49 | H7: May | I7: 632784.87 | J7: 170728.16 | L7: Grand Total | M7: 5095204 | N7: 1364022.7 | P7: New Michele | Q7: 287036.32 | S7: Under 25 | T7: 617861.73
D8: Electronics | E8: Laptop | F8: 67878.58 | H8: Jun | I8: 679817.81 | J8: 181803.3 | P8: Grand Total | Q8: 1364022.7 | S8: Grand Total | T8: 5095204
B9: Sales | E9: Headphones | F9: 78434.213 | H9: Jul | I9: 610693.28 | J9: 157140.2
B10: =GETPIVOTDATA("Net Revenue",$B$2) -> 5095204 | E10: Camera | F10: 79980.384 | H10: Aug | I10: 587098.41 | J10: 150720.76
B11: Profit | E11: Television | F11: 127999.22 | H11: Sept | I11: 145960.41 | J11: 39771.86
B12: =GETPIVOTDATA("Profit",$B$6) -> 1364022.7 | E12: Smartphone | F12: 193414.42 | H12: Grand Total | I12: 5095204 | J12: 1364022.7
D13: Electronics Total | F13: 547706.82
B14: Profit Margin | D14: Fashion | E14: Bags | F14: 65880.34
B15: =(B12 /B10) -> 0.26770719 | E15: Watches | F15: 96943.475
E16: Clothing | F16: 132990.6
E17: Footwear | F17: 151327.53
E18: Accessories | F18: 161167.5
D19: Fashion Total | F19: 608309.43
D20: Grand Total | F20: 1364022.7

Sheet Dashboard
W27: S
